{"version":"1.0","encoding":"UTF-8","feed":{"xmlns":"http://www.w3.org/2005/Atom","xmlns$openSearch":"http://a9.com/-/spec/opensearch/1.1/","xmlns$gd":"http://schemas.google.com/g/2005","gd$etag":"W/\"DEcBSHk4eSp7ImA9XBNSFU8.\"","id":{"$t":"tag:blogger.com,1999:blog-5235590154125226279.post7572636608525031391..comments"},"updated":{"$t":"2019-03-02T19:27:39.731+08:00"},"title":{"$t":"Comments on 编程随想的博客: 开源实践：SQLite 的使用场景"},"link":[{"rel":"http://schemas.google.com/g/2005#feed","type":"application/atom+xml","href":"https:\/\/program-think.blogspot.com\/feeds\/comments\/default"},{"rel":"self","type":"application/atom+xml","href":"https:\/\/www.blogger.com\/feeds\/5235590154125226279\/7572636608525031391\/comments\/default?alt=json\u0026max-results=10000\u0026reverse=false\u0026orderby=published\u0026v=2"},{"rel":"alternate","type":"text/html","href":"https:\/\/program-think.blogspot.com\/2009\/04\/how-to-use-sqlite.html"},{"rel":"hub","href":"http://pubsubhubbub.appspot.com/"}],"author":[{"name":{"$t":"编程随想"},"uri":{"$t":"http:\/\/www.blogger.com\/profile\/11741356469378252621"},"email":{"$t":"noreply@blogger.com"},"gd$image":{"rel":"http://schemas.google.com/g/2005#thumbnail","width":"26","height":"32","src":"\/\/4.bp.blogspot.com\/-GTIh2pdzDYI\/VtcrB6rX0pI\/AAAAAAAABUg\/vWdDxEU4N6c\/s220\/Thinker.jpg"}}],"generator":{"version":"7.00","uri":"http://www.blogger.com","$t":"Blogger"},"openSearch$totalResults":{"$t":"8"},"openSearch$startIndex":{"$t":"1"},"openSearch$itemsPerPage":{"$t":"10000"},"entry":[{"gd$etag":"W/\"DEEMQX47eCp7ImA9WxJTGUQ.\"","id":{"$t":"tag:blogger.com,1999:blog-5235590154125226279.post-5854644586173535013"},"published":{"$t":"2009-04-29T17:18:00.000+08:00"},"updated":{"$t":"2009-04-29T17:18:00.000+08:00"},"app$edited":{"xmlns$app":"http://www.w3.org/2007/app","$t":"2009-04-29T17:18:00.000+08:00"},"title":{"$t":"看你的文章是种享受，多加油哦"},"content":{"type":"html","$t":"看你的文章是种享受，多加油哦"},"link":[{"rel":"edit","type":"application/atom+xml","href":"https:\/\/www.blogger.com\/feeds\/5235590154125226279\/7572636608525031391\/comments\/default\/5854644586173535013?v=2"},{"rel":"self","type":"application/atom+xml","href":"https:\/\/www.blogger.com\/feeds\/5235590154125226279\/7572636608525031391\/comments\/default\/5854644586173535013?v=2"},{"rel":"alternate","type":"text/html","href":"https:\/\/program-think.blogspot.com\/2009\/04\/how-to-use-sqlite.html?showComment=1240996680000#c5854644586173535013","title":""}],"author":[{"name":{"$t":"epicxiao"},"email":{"$t":"noreply@blogger.com"},"gd$image":{"rel":"http://schemas.google.com/g/2005#thumbnail","width":"16","height":"16","src":"https:\/\/img1.blogblog.com\/img\/blank.gif"}}],"thr$in-reply-to":{"xmlns$thr":"http://purl.org/syndication/thread/1.0","href":"https:\/\/program-think.blogspot.com\/2009\/04\/how-to-use-sqlite.html","ref":"tag:blogger.com,1999:blog-5235590154125226279.post-7572636608525031391","source":"http://www.blogger.com/feeds/5235590154125226279/posts/default/7572636608525031391","type":"text/html"},"gd$extendedProperty":[{"name":"blogger.itemClass","value":"pid-357517073"},{"name":"blogger.displayTime","value":"2009年4月29日 下午5:18:00"}]},{"gd$etag":"W/\"DU4MQX47eCp7ImA9WxJSEEw.\"","id":{"$t":"tag:blogger.com,1999:blog-5235590154125226279.post-4557325269797263614"},"published":{"$t":"2009-04-29T23:13:00.000+08:00"},"updated":{"$t":"2009-04-29T23:13:00.000+08:00"},"app$edited":{"xmlns$app":"http://www.w3.org/2007/app","$t":"2009-04-29T23:13:00.000+08:00"},"title":{"$t":"多谢楼上同学鼓励 :)"},"content":{"type":"html","$t":"多谢楼上同学鼓励 :)"},"link":[{"rel":"edit","type":"application/atom+xml","href":"https:\/\/www.blogger.com\/feeds\/5235590154125226279\/7572636608525031391\/comments\/default\/4557325269797263614?v=2"},{"rel":"self","type":"application/atom+xml","href":"https:\/\/www.blogger.com\/feeds\/5235590154125226279\/7572636608525031391\/comments\/default\/4557325269797263614?v=2"},{"rel":"alternate","type":"text/html","href":"https:\/\/program-think.blogspot.com\/2009\/04\/how-to-use-sqlite.html?showComment=1241017980000#c4557325269797263614","title":""}],"author":[{"name":{"$t":"编程随想"},"uri":{"$t":"https:\/\/www.blogger.com\/profile\/11741356469378252621"},"email":{"$t":"noreply@blogger.com"},"gd$image":{"rel":"http://schemas.google.com/g/2005#thumbnail","width":"26","height":"32","src":"http:\/\/4.bp.blogspot.com\/_itipB8vBZzQ\/SY1isusKAfI\/AAAAAAAAAGo\/4YF360m0Yto\/S220\/Thinker_BlogSpot.jpg"}}],"thr$in-reply-to":{"xmlns$thr":"http://purl.org/syndication/thread/1.0","href":"https:\/\/program-think.blogspot.com\/2009\/04\/how-to-use-sqlite.html","ref":"tag:blogger.com,1999:blog-5235590154125226279.post-7572636608525031391","source":"http://www.blogger.com/feeds/5235590154125226279/posts/default/7572636608525031391","type":"text/html"},"gd$extendedProperty":[{"name":"blogger.itemClass","value":"pid-1582521586"},{"name":"blogger.displayTime","value":"2009年4月29日 下午11:13:00"}]},{"gd$etag":"W/\"Ak8GQX47eCp7ImA9WxJSEkg.\"","id":{"$t":"tag:blogger.com,1999:blog-5235590154125226279.post-2130135457485248536"},"published":{"$t":"2009-05-02T18:07:00.000+08:00"},"updated":{"$t":"2009-05-02T18:07:00.000+08:00"},"app$edited":{"xmlns$app":"http://www.w3.org/2007/app","$t":"2009-05-02T18:07:00.000+08:00"},"title":{"$t":"向前辈学习了！"},"content":{"type":"html","$t":"向前辈学习了！"},"link":[{"rel":"edit","type":"application/atom+xml","href":"https:\/\/www.blogger.com\/feeds\/5235590154125226279\/7572636608525031391\/comments\/default\/2130135457485248536?v=2"},{"rel":"self","type":"application/atom+xml","href":"https:\/\/www.blogger.com\/feeds\/5235590154125226279\/7572636608525031391\/comments\/default\/2130135457485248536?v=2"},{"rel":"alternate","type":"text/html","href":"https:\/\/program-think.blogspot.com\/2009\/04\/how-to-use-sqlite.html?showComment=1241258820000#c2130135457485248536","title":""}],"author":[{"name":{"$t":"Anonymous"},"email":{"$t":"noreply@blogger.com"},"gd$image":{"rel":"http://schemas.google.com/g/2005#thumbnail","width":"16","height":"16","src":"https:\/\/img1.blogblog.com\/img\/blank.gif"}}],"thr$in-reply-to":{"xmlns$thr":"http://purl.org/syndication/thread/1.0","href":"https:\/\/program-think.blogspot.com\/2009\/04\/how-to-use-sqlite.html","ref":"tag:blogger.com,1999:blog-5235590154125226279.post-7572636608525031391","source":"http://www.blogger.com/feeds/5235590154125226279/posts/default/7572636608525031391","type":"text/html"},"gd$extendedProperty":[{"name":"blogger.itemClass","value":"pid-357517073"},{"name":"blogger.displayTime","value":"2009年5月2日 下午6:07:00"}]},{"gd$etag":"W/\"D0cAQH8zeSp7ImA9WxJbF0k.\"","id":{"$t":"tag:blogger.com,1999:blog-5235590154125226279.post-1619239573460754726"},"published":{"$t":"2009-07-28T09:37:21.181+08:00"},"updated":{"$t":"2009-07-28T09:37:21.181+08:00"},"app$edited":{"xmlns$app":"http://www.w3.org/2007/app","$t":"2009-07-28T09:37:21.181+08:00"},"title":{"$t":"这篇总结得很好。\nAccess和Sqlite我都用来做过项目，确实各有所长。SQLite轻便，且跨平..."},"content":{"type":"html","$t":"这篇总结得很好。\u003Cbr \/\u003EAccess和Sqlite我都用来做过项目，确实各有所长。SQLite轻便，且跨平台，这是优势，缺点是没有 Access 那样强大的管理界面。"},"link":[{"rel":"edit","type":"application/atom+xml","href":"https:\/\/www.blogger.com\/feeds\/5235590154125226279\/7572636608525031391\/comments\/default\/1619239573460754726?v=2"},{"rel":"self","type":"application/atom+xml","href":"https:\/\/www.blogger.com\/feeds\/5235590154125226279\/7572636608525031391\/comments\/default\/1619239573460754726?v=2"},{"rel":"alternate","type":"text/html","href":"https:\/\/program-think.blogspot.com\/2009\/04\/how-to-use-sqlite.html?showComment=1248745041181#c1619239573460754726","title":""}],"author":[{"name":{"$t":"Jlake"},"uri":{"$t":"https:\/\/www.blogger.com\/profile\/10978850539298578884"},"email":{"$t":"noreply@blogger.com"},"gd$image":{"rel":"http://schemas.google.com/g/2005#thumbnail","width":"16","height":"16","src":"https:\/\/img1.blogblog.com\/img\/b16-rounded.gif"}}],"thr$in-reply-to":{"xmlns$thr":"http://purl.org/syndication/thread/1.0","href":"https:\/\/program-think.blogspot.com\/2009\/04\/how-to-use-sqlite.html","ref":"tag:blogger.com,1999:blog-5235590154125226279.post-7572636608525031391","source":"http://www.blogger.com/feeds/5235590154125226279/posts/default/7572636608525031391","type":"text/html"},"gd$extendedProperty":[{"name":"blogger.itemClass","value":"pid-209105988"},{"name":"blogger.displayTime","value":"2009年7月28日 上午9:37:00"}]},{"gd$etag":"W/\"A0cBSHo6fCp7ImA9WxJbF0g.\"","id":{"$t":"tag:blogger.com,1999:blog-5235590154125226279.post-1913468435558484886"},"published":{"$t":"2009-07-28T13:30:59.414+08:00"},"updated":{"$t":"2009-07-28T13:30:59.414+08:00"},"app$edited":{"xmlns$app":"http://www.w3.org/2007/app","$t":"2009-07-28T13:30:59.414+08:00"},"title":{"$t":"楼上同学说的有理，SQLite确实没有Access那么易用的操作界面。"},"content":{"type":"html","$t":"楼上同学说的有理，SQLite确实没有Access那么易用的操作界面。"},"link":[{"rel":"edit","type":"application/atom+xml","href":"https:\/\/www.blogger.com\/feeds\/5235590154125226279\/7572636608525031391\/comments\/default\/1913468435558484886?v=2"},{"rel":"self","type":"application/atom+xml","href":"https:\/\/www.blogger.com\/feeds\/5235590154125226279\/7572636608525031391\/comments\/default\/1913468435558484886?v=2"},{"rel":"alternate","type":"text/html","href":"https:\/\/program-think.blogspot.com\/2009\/04\/how-to-use-sqlite.html?showComment=1248759059414#c1913468435558484886","title":""}],"author":[{"name":{"$t":"编程随想"},"uri":{"$t":"https:\/\/www.blogger.com\/profile\/11741356469378252621"},"email":{"$t":"noreply@blogger.com"},"gd$image":{"rel":"http://schemas.google.com/g/2005#thumbnail","width":"26","height":"32","src":"http:\/\/4.bp.blogspot.com\/_itipB8vBZzQ\/SY1isusKAfI\/AAAAAAAAAGo\/4YF360m0Yto\/S220\/Thinker_BlogSpot.jpg"}}],"thr$in-reply-to":{"xmlns$thr":"http://purl.org/syndication/thread/1.0","href":"https:\/\/program-think.blogspot.com\/2009\/04\/how-to-use-sqlite.html","ref":"tag:blogger.com,1999:blog-5235590154125226279.post-7572636608525031391","source":"http://www.blogger.com/feeds/5235590154125226279/posts/default/7572636608525031391","type":"text/html"},"gd$extendedProperty":[{"name":"blogger.itemClass","value":"pid-1582521586"},{"name":"blogger.displayTime","value":"2009年7月28日 下午1:30:00"}]},{"gd$etag":"W/\"CU8GQH07fCp7ImA9WhJVEUk.\"","id":{"$t":"tag:blogger.com,1999:blog-5235590154125226279.post-8495223531372371956"},"published":{"$t":"2012-08-28T16:50:21.304+08:00"},"updated":{"$t":"2012-08-28T16:50:21.304+08:00"},"app$edited":{"xmlns$app":"http://www.w3.org/2007/app","$t":"2012-08-28T16:50:21.304+08:00"},"title":{"$t":"SQLite也有GUI工具的"},"content":{"type":"html","$t":"SQLite也有GUI工具的"},"link":[{"rel":"edit","type":"application/atom+xml","href":"https:\/\/www.blogger.com\/feeds\/5235590154125226279\/7572636608525031391\/comments\/default\/8495223531372371956?v=2"},{"rel":"self","type":"application/atom+xml","href":"https:\/\/www.blogger.com\/feeds\/5235590154125226279\/7572636608525031391\/comments\/default\/8495223531372371956?v=2"},{"rel":"alternate","type":"text/html","href":"https:\/\/program-think.blogspot.com\/2009\/04\/how-to-use-sqlite.html?showComment=1346143821304#c8495223531372371956","title":""}],"author":[{"name":{"$t":"Anonymous"},"email":{"$t":"noreply@blogger.com"},"gd$image":{"rel":"http://schemas.google.com/g/2005#thumbnail","width":"16","height":"16","src":"https:\/\/img1.blogblog.com\/img\/blank.gif"}}],"thr$in-reply-to":{"xmlns$thr":"http://purl.org/syndication/thread/1.0","href":"https:\/\/program-think.blogspot.com\/2009\/04\/how-to-use-sqlite.html","ref":"tag:blogger.com,1999:blog-5235590154125226279.post-7572636608525031391","source":"http://www.blogger.com/feeds/5235590154125226279/posts/default/7572636608525031391","type":"text/html"},"gd$extendedProperty":[{"name":"blogger.itemClass","value":"pid-558301384"},{"name":"blogger.displayTime","value":"2012年8月28日 下午4:50:00"}]},{"gd$etag":"W/\"CE4EQ3Y4eCp7ImA9WhJVEkg.\"","id":{"$t":"tag:blogger.com,1999:blog-5235590154125226279.post-4688906939024689601"},"published":{"$t":"2012-08-29T23:08:22.830+08:00"},"updated":{"$t":"2012-08-29T23:08:22.830+08:00"},"app$edited":{"xmlns$app":"http://www.w3.org/2007/app","$t":"2012-08-29T23:08:22.830+08:00"},"title":{"$t":"TO 楼上的网友\nSQLite 本身没有自带的 GUI 工具，只有命令行工具。而 Access 的 ..."},"content":{"type":"html","$t":"TO 楼上的网友\u003Cbr \/\u003ESQLite 本身没有自带的 GUI 工具，只有命令行工具。而 Access 的 GUI 界面是自带的。\u003Cbr \/\u003E所以俺才说：“SQLite确实没有Access那么易用的操作界面”\u003Cbr \/\u003E\u003Cbr \/\u003E不过第三方的 SQLite 工具中，倒是有几个很不错的，比如 SQLite Developer"},"link":[{"rel":"edit","type":"application/atom+xml","href":"https:\/\/www.blogger.com\/feeds\/5235590154125226279\/7572636608525031391\/comments\/default\/4688906939024689601?v=2"},{"rel":"self","type":"application/atom+xml","href":"https:\/\/www.blogger.com\/feeds\/5235590154125226279\/7572636608525031391\/comments\/default\/4688906939024689601?v=2"},{"rel":"alternate","type":"text/html","href":"https:\/\/program-think.blogspot.com\/2009\/04\/how-to-use-sqlite.html?showComment=1346252902830#c4688906939024689601","title":""}],"author":[{"name":{"$t":"编程随想"},"uri":{"$t":"https:\/\/www.blogger.com\/profile\/11741356469378252621"},"email":{"$t":"noreply@blogger.com"},"gd$image":{"rel":"http://schemas.google.com/g/2005#thumbnail","width":"26","height":"32","src":"http:\/\/1.bp.blogspot.com\/-AmZd_cbsMA8\/Th5EbQ2_22I\/AAAAAAAAAfg\/loksvIqGzic\/s220\/Thinker.jpg"}}],"thr$in-reply-to":{"xmlns$thr":"http://purl.org/syndication/thread/1.0","href":"https:\/\/program-think.blogspot.com\/2009\/04\/how-to-use-sqlite.html","ref":"tag:blogger.com,1999:blog-5235590154125226279.post-7572636608525031391","source":"http://www.blogger.com/feeds/5235590154125226279/posts/default/7572636608525031391","type":"text/html"},"gd$extendedProperty":[{"name":"blogger.itemClass","value":"pid-1582521586"},{"name":"blogger.displayTime","value":"2012年8月29日 下午11:08:00"}]},{"gd$etag":"W/\"DEcFSHk_eip7ImA9XRRQE0s.\"","id":{"$t":"tag:blogger.com,1999:blog-5235590154125226279.post-3918563909235430704"},"published":{"$t":"2015-02-08T11:26:59.742+08:00"},"updated":{"$t":"2015-02-08T11:26:59.742+08:00"},"app$edited":{"xmlns$app":"http://www.w3.org/2007/app","$t":"2015-02-08T11:26:59.742+08:00"},"title":{"$t":"我在php上使用sqlite3经常遇到数据库未初始化的错误。。到处查资料都找不到原因"},"content":{"type":"html","$t":"我在php上使用sqlite3经常遇到数据库未初始化的错误。。到处查资料都找不到原因"},"link":[{"rel":"edit","type":"application/atom+xml","href":"https:\/\/www.blogger.com\/feeds\/5235590154125226279\/7572636608525031391\/comments\/default\/3918563909235430704?v=2"},{"rel":"self","type":"application/atom+xml","href":"https:\/\/www.blogger.com\/feeds\/5235590154125226279\/7572636608525031391\/comments\/default\/3918563909235430704?v=2"},{"rel":"alternate","type":"text/html","href":"https:\/\/program-think.blogspot.com\/2009\/04\/how-to-use-sqlite.html?showComment=1423366019742#c3918563909235430704","title":""}],"author":[{"name":{"$t":"WVza2l0b2t"},"uri":{"$t":"http:\/\/www.fuckgfw.com"},"email":{"$t":"noreply@blogger.com"},"gd$image":{"rel":"http://schemas.google.com/g/2005#thumbnail","width":"16","height":"16","src":"https:\/\/img1.blogblog.com\/img\/blank.gif"}}],"thr$in-reply-to":{"xmlns$thr":"http://purl.org/syndication/thread/1.0","href":"https:\/\/program-think.blogspot.com\/2009\/04\/how-to-use-sqlite.html","ref":"tag:blogger.com,1999:blog-5235590154125226279.post-7572636608525031391","source":"http://www.blogger.com/feeds/5235590154125226279/posts/default/7572636608525031391","type":"text/html"},"gd$extendedProperty":[{"name":"blogger.itemClass","value":"pid-40484010"},{"name":"blogger.displayTime","value":"2015年2月8日 上午11:26:00"}]}]}}